powerline_ifinfo/__init__.py
powerline_ifinfo/ifinfo.py
powerline_ifinfo_segment-1.0.1.dist-info/LICENSE
powerline_ifinfo_segment-1.0.1.dist-info/METADATA
powerline_ifinfo_segment-1.0.1.dist-info/WHEEL
powerline_ifinfo_segment-1.0.1.dist-info/top_level.txt
powerline_ifinfo_segment-1.0.1.dist-info/RECORD
